<?xml version="1.0" encoding="utf-8" ?>
<dwsync>
<file name="13_G_1413784843424.jpg" server="qyu1273800001.my3w.com//htdocs/" local="130582584000000000" remote="130582584000000000" />
<file name="13_P_1413784769703.jpg" server="qyu1273800001.my3w.com//htdocs/" local="130582583400000000" remote="130582583400000000" />
<file name="13_P_1413784843928.jpg" server="qyu1273800001.my3w.com//htdocs/" local="130582584000000000" remote="130582584000000000" />
<file name="51_G_1413784922772.jpg" server="qyu1273800001.my3w.com//htdocs/" local="130582585200000000" remote="130582585200000000" />
<file name="51_P_1413784923341.jpg" server="qyu1273800001.my3w.com//htdocs/" local="130582585200000000" remote="130582585200000000" />
<file name="52_G_1413857979039.jpg" server="qyu1273800001.my3w.com//htdocs/" local="130583315400000000" remote="130583315400000000" />
<file name="52_P_1413857979582.jpg" server="qyu1273800001.my3w.com//htdocs/" local="130583315400000000" remote="130583315400000000" />
<file name="53_G_1413858103613.jpg" server="qyu1273800001.my3w.com//htdocs/" local="130583316600000000" remote="130583316600000000" />
<file name="53_P_1413858103338.jpg" server="qyu1273800001.my3w.com//htdocs/" local="130583316600000000" remote="130583316600000000" />
<file name="54_G_1413858246271.jpg" server="qyu1273800001.my3w.com//htdocs/" local="130583318400000000" remote="130583318400000000" />
<file name="54_P_1413858246877.jpg" server="qyu1273800001.my3w.com//htdocs/" local="130583318400000000" remote="130583318400000000" />
<file name="55_G_1413858361405.jpg" server="qyu1273800001.my3w.com//htdocs/" local="130583319600000000" remote="130583319600000000" />
<file name="55_P_1413858361154.jpg" server="qyu1273800001.my3w.com//htdocs/" local="130583319600000000" remote="130583319600000000" />
<file name="56_G_1413858586768.jpg" server="qyu1273800001.my3w.com//htdocs/" local="130583321400000000" remote="130583321400000000" />
<file name="56_P_1413858586294.jpg" server="qyu1273800001.my3w.com//htdocs/" local="130583321400000000" remote="130583321400000000" />
<file name="57_G_1413858649314.jpg" server="qyu1273800001.my3w.com//htdocs/" local="130583322000000000" remote="130583322000000000" />
<file name="57_P_1413858649915.jpg" server="qyu1273800001.my3w.com//htdocs/" local="130583322000000000" remote="130583322000000000" />
<file name="58_G_1413870146699.jpg" server="qyu1273800001.my3w.com//htdocs/" local="130583437200000000" remote="130583437200000000" />
<file name="58_P_1413870146735.jpg" server="qyu1273800001.my3w.com//htdocs/" local="130583437200000000" remote="130583437200000000" />
<file name="59_G_1413870251072.jpg" server="qyu1273800001.my3w.com//htdocs/" local="130583438400000000" remote="130583438400000000" />
<file name="59_P_1413870251292.jpg" server="qyu1273800001.my3w.com//htdocs/" local="130583438400000000" remote="130583438400000000" />
<file name="60_G_1413870314637.jpg" server="qyu1273800001.my3w.com//htdocs/" local="130583439000000000" remote="130583439000000000" />
<file name="60_P_1413870314004.jpg" server="qyu1273800001.my3w.com//htdocs/" local="130583439000000000" remote="130583439000000000" />
<file name="61_G_1413871141750.jpg" server="qyu1273800001.my3w.com//htdocs/" local="130583447400000000" remote="130583447400000000" />
<file name="61_P_1413871141372.jpg" server="qyu1273800001.my3w.com//htdocs/" local="130583447400000000" remote="130583447400000000" />
<file name="62_G_1413871301695.jpg" server="qyu1273800001.my3w.com//htdocs/" local="130583448600000000" remote="130583448600000000" />
<file name="62_P_1413871301328.jpg" server="qyu1273800001.my3w.com//htdocs/" local="130583448600000000" remote="130583448600000000" />
<file name="63_G_1413871371280.jpg" server="qyu1273800001.my3w.com//htdocs/" local="130583449200000000" remote="130583449200000000" />
<file name="63_P_1413871371104.jpg" server="qyu1273800001.my3w.com//htdocs/" local="130583449200000000" remote="130583449200000000" />
<file name="64_G_1413871508224.jpg" server="qyu1273800001.my3w.com//htdocs/" local="130583451000000000" remote="130583451000000000" />
<file name="64_P_1413871508351.jpg" server="qyu1273800001.my3w.com//htdocs/" local="130583451000000000" remote="130583451000000000" />
<file name="65_G_1413871589257.jpg" server="qyu1273800001.my3w.com//htdocs/" local="130583451600000000" remote="130583451600000000" />
<file name="65_P_1413871589034.jpg" server="qyu1273800001.my3w.com//htdocs/" local="130583451600000000" remote="130583451600000000" />
<file name="66_G_1413879844893.jpg" server="qyu1273800001.my3w.com//htdocs/" local="130583534400000000" remote="130583534400000000" />
<file name="66_P_1413879844114.jpg" server="qyu1273800001.my3w.com//htdocs/" local="130583534400000000" remote="130583534400000000" />
<file name="67_G_1413879924982.jpg" server="qyu1273800001.my3w.com//htdocs/" local="130583535000000000" remote="130583535000000000" />
<file name="67_P_1413879924961.jpg" server="qyu1273800001.my3w.com//htdocs/" local="130583535000000000" remote="130583535000000000" />
<file name="68_G_1413879999297.jpg" server="qyu1273800001.my3w.com//htdocs/" local="130583535600000000" remote="130583535600000000" />
<file name="68_P_1413879999793.jpg" server="qyu1273800001.my3w.com//htdocs/" local="130583535600000000" remote="130583535600000000" />
<file name="69_G_1413880089977.jpg" server="qyu1273800001.my3w.com//htdocs/" local="130583536800000000" remote="130583536800000000" />
<file name="69_P_1413880089317.jpg" server="qyu1273800001.my3w.com//htdocs/" local="130583536800000000" remote="130583536800000000" />
<file name="70_G_1413880216199.jpg" server="qyu1273800001.my3w.com//htdocs/" local="130583538000000000" remote="130583538000000000" />
<file name="70_P_1413880216090.jpg" server="qyu1273800001.my3w.com//htdocs/" local="130583538000000000" remote="130583538000000000" />
<file name="71_G_1413880295295.jpg" server="qyu1273800001.my3w.com//htdocs/" local="130583538600000000" remote="130583538600000000" />
<file name="71_P_1413880295294.jpg" server="qyu1273800001.my3w.com//htdocs/" local="130583538600000000" remote="130583538600000000" />
<file name="72_G_1413880382413.jpg" server="qyu1273800001.my3w.com//htdocs/" local="130583539800000000" remote="130583539800000000" />
<file name="72_P_1413880382727.jpg" server="qyu1273800001.my3w.com//htdocs/" local="130583539800000000" remote="130583539800000000" />
<file name="73_G_1413880463957.jpg" server="qyu1273800001.my3w.com//htdocs/" local="130583540400000000" remote="130583540400000000" />
<file name="73_P_1413880463976.jpg" server="qyu1273800001.my3w.com//htdocs/" local="130583540400000000" remote="130583540400000000" />
</dwsync>