<?xml version="1.0" encoding="utf-8" ?>
<dwsync>
<file name="cac.php" server="qyu1273800001.my3w.com//htdocs/" local="130452480000000000" remote="130452480000000000" />
<file name="city_express.php" server="qyu1273800001.my3w.com//htdocs/" local="130452480000000000" remote="130452480000000000" />
<file name="ems.php" server="qyu1273800001.my3w.com//htdocs/" local="130452480000000000" remote="130452480000000000" />
<file name="flat.php" server="qyu1273800001.my3w.com//htdocs/" local="130452480000000000" remote="130452480000000000" />
<file name="fpd.php" server="qyu1273800001.my3w.com//htdocs/" local="130452480000000000" remote="130452480000000000" />
<file name="post_express.php" server="qyu1273800001.my3w.com//htdocs/" local="130452480000000000" remote="130452480000000000" />
<file name="post_mail.php" server="qyu1273800001.my3w.com//htdocs/" local="130452480000000000" remote="130452480000000000" />
<file name="presswork.php" server="qyu1273800001.my3w.com//htdocs/" local="130452480000000000" remote="130452480000000000" />
<file name="sf_express.php" server="qyu1273800001.my3w.com//htdocs/" local="130452480000000000" remote="130452480000000000" />
<file name="sto_express.php" server="qyu1273800001.my3w.com//htdocs/" local="130452480000000000" remote="130452480000000000" />
<file name="yto.php" server="qyu1273800001.my3w.com//htdocs/" local="130452480000000000" remote="130452480000000000" />
<file name="zto.php" server="qyu1273800001.my3w.com//htdocs/" local="130452480000000000" remote="130452480000000000" />
</dwsync>